{
  "name": "zoon",
  "tests": "./e2e/tests/*.js",
  "output": "./e2e/output",
  "bootstrap": "./e2e/bootstrap_and_teardown.js",
  "teardown": "./e2e/bootstrap_and_teardown.js",
  "helpers": {
    "Nightmare": {
      "url": "http://localhost:3000",
      "show": false
    },
    "ExternalCommand": {
      "require": "./e2e/helpers/ExternalCommand.js"
    },
    "DatabaseReset": {
      "require": "./e2e/helpers/DatabaseReset.js"
    }
  },
  "include": {
    "I": "./e2e/steps/I.js"
  },
  "mocha": {}
}
